{
  "slug": "politics",
  "kind": "subject",
  "title": "Politics Signals",
  "summary": "Politics is the live layer for power, legitimacy, lawmaking, policy execution, public trust, and institutional stress. The useful habit is to read signals structurally, not just as personalities and outrage.",
  "sections": [
    {
      "slug": "major-developments",
      "title": "Major Developments",
      "items": [
        {
          "name": "Democratic trust is increasingly a governance problem",
          "summary": "Politics in many democracies is under pressure from distrust, fragmentation, and weak confidence in institutions.",
          "whyItMatters": "Legitimacy is not decorative. It is part of whether systems can still govern effectively.",
          "entities": ["politics", "public-administration", "world-history"]
        },
        {
          "name": "Domestic politics and geopolitics are bleeding into one another",
          "summary": "Trade, energy, migration, defence, and supply chains increasingly shape internal political argument.",
          "whyItMatters": "The line between national policy and international strategy is thinner than it used to be.",
          "entities": ["geopolitics", "energy", "supply-chain-logistics"]
        },
        {
          "name": "Political communication is now platform-mediated",
          "summary": "Social media, creator ecosystems, algorithmic feeds, and synthetic media increasingly shape what political attention looks like.",
          "whyItMatters": "Power now moves through information systems as much as through chambers and speeches.",
          "entities": ["communication", "artificial-intelligence", "Meta"]
        }
      ]
    },
    {
      "slug": "important-companies",
      "title": "Important Companies",
      "items": [
        {
          "name": "Meta",
          "summary": "Still central to how political communication, moderation, and public debate are distributed.",
          "whyItMatters": "Platform design shapes the information environment political actors have to operate inside.",
          "entities": ["communication", "politics"]
        },
        {
          "name": "Google",
          "summary": "Search, video, and advertising still influence agenda-setting and information discovery.",
          "whyItMatters": "Search and video remain major gateways to public understanding.",
          "entities": ["communication", "data-science", "politics"]
        },
        {
          "name": "NationBuilder",
          "summary": "A visible example of how campaign and organising infrastructure has become software-mediated.",
          "whyItMatters": "Political operations increasingly rely on tooling, data hygiene, and supporter systems.",
          "entities": ["politics", "communication"]
        }
      ]
    },
    {
      "slug": "important-institutions",
      "title": "Important Institutions",
      "items": [
        {
          "name": "Parliament of Australia",
          "summary": "The core public site of lawmaking, scrutiny, and representative legitimacy at the federal level.",
          "whyItMatters": "It remains the formal arena where political authority is translated into public decisions.",
          "entities": ["law", "public-administration", "politics"]
        },
        {
          "name": "Australian Electoral Commission",
          "summary": "The institution that keeps election administration credible and visible.",
          "whyItMatters": "Electoral integrity is one of the key foundations of legitimacy.",
          "entities": ["law", "demography", "politics"]
        },
        {
          "name": "ANAO and integrity architecture",
          "summary": "Audit and integrity bodies shape how public failure gets surfaced and corrected.",
          "whyItMatters": "Political trust depends partly on visible correction mechanisms.",
          "entities": ["public-administration", "law", "politics"]
        }
      ]
    },
    {
      "slug": "notable-people",
      "title": "Notable People",
      "items": [
        {
          "name": "Machiavelli",
          "summary": "Still one of the sharpest lenses on power, incentives, and statecraft.",
          "whyItMatters": "He remains useful because politics rarely stops being a problem of power under uncertainty.",
          "entities": ["politics", "diplomat"]
        },
        {
          "name": "Hannah Arendt",
          "summary": "A central thinker on authority, public life, totalitarianism, and the conditions of political judgment.",
          "whyItMatters": "She keeps politics connected to moral and institutional seriousness.",
          "entities": ["politics", "philosophy"]
        },
        {
          "name": "Anne Twomey",
          "summary": "A practical Australian guide for constitutional and institutional explanation.",
          "whyItMatters": "She is one of the clearest mature interpreters when Australian institutions are under stress or confusion.",
          "entities": ["politics", "law"]
        }
      ]
    },
    {
      "slug": "active-debates",
      "title": "Active Debates",
      "items": [
        {
          "name": "Institutions versus anti-establishment politics",
          "summary": "A core modern debate is whether to strengthen institutions or distrust them as obstacles to change.",
          "whyItMatters": "This tension shapes public trust and the durability of democratic systems.",
          "entities": ["public-administration", "world-history", "politics"]
        },
        {
          "name": "How much should digital platforms shape public discourse?",
          "summary": "Speech, moderation, misinformation, and algorithmic amplification remain deeply contested.",
          "whyItMatters": "The architecture of public attention is becoming a constitutional-scale political issue.",
          "entities": ["communication", "artificial-intelligence", "law"]
        },
        {
          "name": "Can democracies stay strategic under long-term pressure?",
          "summary": "Security, climate, industry, and fiscal pressure all demand longer-term political coordination than many systems reward.",
          "whyItMatters": "This is really a debate about whether modern democratic politics can still handle sustained strategic problems.",
          "entities": ["geopolitics", "energy", "public-administration"]
        }
      ]
    }
  ]
}
