{
  "slug": "experimentation-analysis-in-practice",
  "title": "Experimentation Analysis in Practice",
  "shortSummary": "Build stronger experimentation analysis in practice judgment so data / analytics work becomes clearer, more repeatable, and easier to lead.",
  "level": "intermediate",
  "domain": "data-analytics",
  "whyItMatters": "Experimentation Analysis in Practice is a leverage point inside data / analytics. It supports the broader goal of kpis, dashboards, instrumentation, and interpreting signals.",
  "coreConcepts": [
    "Experimentation Analysis in Practice needs clear definitions before it can become a reliable operating system.",
    "Good experimentation analysis in practice work depends on better signal, better sequencing, and cleaner ownership.",
    "Experimentation Analysis in Practice should reduce rework and improve the quality of decisions across the business."
  ],
  "lessons": [
    "experimentation-analysis-in-practice-lesson"
  ],
  "frameworks": [
    "privacy-boundaries-roadmap",
    "insight-communication-playbook-lens"
  ],
  "relatedModules": [
    "experimentation-analysis-foundations",
    "data-quality-foundations"
  ],
  "status": "complete",
  "order": 10,
  "levelNumber": 10,
  "category": "strategy"
}